{
    "Mon": [
        "DS",
        "OOP",
        "LAB",
        "~",
        "SE",
        "DS",
        "DMS"
    ],
    "Tue": [
        "PE",
        "DMS",
        "LSD",
        "~",
        "DS",
        "OOP",
        "LAB"
    ],
    "Wed": [
        "LSD",
        "DMS",
        "DS",
        "~",
        "OOP",
        "SE",
        "OOP"
    ],
    "Thu": [
        "DS",
        "LSD",
        "OOP",
        "~",
        "PE",
        "MNR",
        "RMD"
    ],
    "Fri": [
        "DBMS",
        "COA",
        "MAT",
        "~",
        "OS",
        "MNR",
        "RMD"
    ]
}
